invarum/__init__.py
invarum/__main__.py
invarum/client.py
invarum/config.py
invarum/main.py
invarum-0.1.6.dist-info/METADATA
invarum-0.1.6.dist-info/WHEEL
invarum-0.1.6.dist-info/entry_points.txt
invarum-0.1.6.dist-info/top_level.txt
invarum-0.1.6.dist-info/RECORD
