Metadata-Version: 2.4
Name: invarum
Version: 0.1.6
Summary: CLI for Invarum, the Governance-grade LLM Quality Engineering platform.
Author-email: "L. Adrian Coleman" <lacolem1@invarum.com>
Project-URL: Homepage, https://app.invarum.com
Project-URL: Repository, https://github.com/Invarum/invarum-cli
Project-URL: Documentation, https://github.com/Invarum/invarum-cli#readme
Classifier: Programming Language :: Python :: 3
Classifier: License :: OSI Approved :: MIT License
Classifier: Operating System :: OS Independent
Classifier: Intended Audience :: Developers
Classifier: Topic :: Software Development :: Quality Assurance
Requires-Python: >=3.9
Requires-Dist: typer[all]>=0.9.0
Requires-Dist: requests>=2.31.0
Requires-Dist: rich>=13.0.0
Requires-Dist: pydantic>=2.0.0
